ddebounce/__init__.py
ddebounce/api.py
ddebounce/lock.py
ddebounce/pytest.py
ddebounce-0.1.0rc0.dist-info/LICENSE
ddebounce-0.1.0rc0.dist-info/METADATA
ddebounce-0.1.0rc0.dist-info/WHEEL
ddebounce-0.1.0rc0.dist-info/entry_points.txt
ddebounce-0.1.0rc0.dist-info/top_level.txt
ddebounce-0.1.0rc0.dist-info/zip-safe
ddebounce-0.1.0rc0.dist-info/RECORD
