Metadata-Version: 2.1
Name: ddebounce
Version: 0.1.0rc0
Summary: UNKNOWN
Home-page: http://github.com/iky/ddebounce
Author: Student.com
License: Apache License, Version 2.0
Platform: UNKNOWN
Classifier: Programming Language :: Python
Classifier: Operating System :: MacOS :: MacOS X
Classifier: Operating System :: POSIX
Classifier: Programming Language :: Python :: 3
Classifier: Programming Language :: Python :: 3.3
Classifier: Programming Language :: Python :: 3.4
Classifier: Programming Language :: Python :: 3.5
Classifier: Programming Language :: Python :: 3.6
Classifier: Programming Language :: Python :: 3.7
Classifier: Topic :: Internet
Classifier: Topic :: Software Development :: Libraries :: Python Modules
Classifier: Intended Audience :: Developers
Requires-Dist: redis (>=2.10.5)
Requires-Dist: wrapt (>=1.10.8)
Provides-Extra: dev
Requires-Dist: coverage (==4.5.2) ; extra == 'dev'
Requires-Dist: eventlet (==0.21.0) ; extra == 'dev'
Requires-Dist: flake8 (==3.6.0) ; extra == 'dev'
Requires-Dist: mock (==2.0.0) ; extra == 'dev'
Requires-Dist: pylint (==2.2.2) ; extra == 'dev'
Requires-Dist: pytest (==4.1.1) ; extra == 'dev'
